driloader/__init__.py
driloader/__main__.py
driloader/driloader.py
driloader/drivers_info.ini
driloader/browser/__init__.py
driloader/browser/basebrowser.py
driloader/browser/chrome.py
driloader/browser/drivers.py
driloader/browser/exceptions.py
driloader/browser/firefox.py
driloader/browser/internet_explorer.py
driloader/config/__init__.py
driloader/config/browser_config.py
driloader/config/config_base.py
driloader/config/paths.py
driloader/factories/__init__.py
driloader/factories/browser_factory.py
driloader/http/__init__.py
driloader/http/operations.py
driloader/http/proxy.py
driloader/utils/__init__.py
driloader/utils/commands.py
driloader/utils/file.py
tests/browser/__init__.py
tests/browser/test_class_chrome.py
driloader-1.2.6.dist-info/LICENSE.txt
driloader-1.2.6.dist-info/METADATA
driloader-1.2.6.dist-info/WHEEL
driloader-1.2.6.dist-info/top_level.txt
driloader-1.2.6.dist-info/RECORD
