Metadata-Version: 2.1
Name: driloader
Version: 1.2.6
Summary: Driver downloader for Selenium
Home-page: UNKNOWN
Author: Lucas Trajano; Felipe Viegas; Jonatha Daguerre
License: MIT
Platform: UNKNOWN
Classifier: Development Status :: 5 - Production/Stable
Classifier: Intended Audience :: Developers
Classifier: Natural Language :: English
Classifier: License :: OSI Approved :: MIT License
Classifier: Programming Language :: Python
Classifier: Programming Language :: Python :: 3.6
Classifier: Programming Language :: Python :: Implementation :: CPython
Classifier: Topic :: Software Development :: Libraries :: Python Modules
Classifier: Topic :: Software Development :: Quality Assurance
Classifier: Topic :: Software Development :: Testing
Requires-Dist: certifi
Requires-Dist: chardet
Requires-Dist: idna
Requires-Dist: requests
Requires-Dist: urllib3
